{
    "category": "Leadership | 2-2.5 hrs",
    "description":"Leadership encompasses the ability to inspire, guide, and influence others towards common goals and objectives. Effective leadership within organizations is essential for creating an environment where diversity, equity, and inclusion (DEI) initiatives can thrive. Leaders play a critical role in setting the tone for organizational culture, policies, and practices.",
    "subcategories": [
        {
            "name":"Caselet 1 | The Promotion Dilemma | 25 Min"
        },
        {
            "name":"Caselet 2 | A Determined Saleswoman In Peshawar | 25 Min"
        },
        {
            "name":"Article 1 | Managment Women And The New Facts Of Life | 20-25 Min"
        },
        {
            "name":"Article 2 | Leaders Aren't Taking Ownership Of Diversity Initiatives, DEI Pros Say | 10 Min"
        },
        {
            "name":"TEDx Talk | How Diversity Makes Teams More Innovative | Rocio Lorenzo | 15 Min"
        }
    ]
}