{
    "category": "Work-Life Balance | 2-2.5 Hrs",
    "description": "The purpose of the Work-Life Balance module is to help organizations create a supportive environment that allows women and men to effectively manage their professional responsibilities alongside personal and family obligations.",
    "subcategories": [
        {
            "name": "Activity | Hopes and Fears | 60 Min"
        },
        {
            "name": "Video 1 | Are You Overly Influenced by Your Own Prejudices? | 10 Min"
        },
        {
            "name": "Caselet | Navigating Work-life Integration Post-Returnship | 15-20 Min"
        },
        {
            "name": "Article | Management Women and the New Facts of Life | 20-25 Min"
        }
    ]
}
